gui/__init__.py
gui/py.typed
gui/start.py
gui/app/__init__.py
gui/app/main_process.py
gui/app/main_window.py
gui/assets/__init__.py
gui/assets/icons/message-square.svg
gui/assets/icons/pause-circle.svg
gui/assets/icons/play-circle.svg
gui/assets/icons/settings.svg
gui/assets/icons/users.svg
gui/assets/styles/theme.qss
gui/assets/theme/__init__.py
gui/assets/theme/styler.py
gui/assets/theme/theme_dark.py
gui/assets/theme/theme_light.py
gui/assets/theme/utils.py
gui/core/__init__.py
gui/core/data_model.py
gui/core/history_model.py
gui/core/log_store.py
gui/views/__init__.py
gui/views/page_agents.py
gui/views/page_environment.py
gui/views/page_home.py
gui/views/page_messages.py
gui/widgets/__init__.py
gui/widgets/agent_card.py
gui/widgets/agent_detail_window.py
gui/widgets/settings_dialog.py
gui/widgets/side_bar.py
gui/widgets/top_bar.py
maspy_gui-2025.12.15.post2.dist-info/METADATA
maspy_gui-2025.12.15.post2.dist-info/WHEEL
maspy_gui-2025.12.15.post2.dist-info/top_level.txt
maspy_gui-2025.12.15.post2.dist-info/RECORD
