Metadata-Version: 2.4
Name: maspy-gui
Version: 2025.12.15.post2
Summary: Interface for the Visual Representation and Debugging of the MASPY Framework
Author: Gabriel Galvan Neres
Author-email: <neres@alunos.utfpr.edu.br>
Keywords: python,autonomous agents,multi-agent system,user interface
Classifier: Development Status :: 5 - Production/Stable
Classifier: Intended Audience :: Developers
Classifier: Programming Language :: Python :: 3.12
Classifier: Operating System :: Unix
Classifier: Operating System :: Microsoft :: Windows
Requires-Dist: maspy-ml>=2025.11.9
Requires-Dist: PyQt5
Dynamic: author
Dynamic: author-email
Dynamic: classifier
Dynamic: description
Dynamic: description-content-type
Dynamic: keywords
Dynamic: requires-dist
Dynamic: summary
